gw/__init__.py
gw/astrology/__init__.py
gw/astrology/igwn_alert_listener.py
gw/astrology/sign_calculator.py
gw_astrology-0.0.1.dist-info/LICENSE
gw_astrology-0.0.1.dist-info/METADATA
gw_astrology-0.0.1.dist-info/WHEEL
gw_astrology-0.0.1.dist-info/entry_points.txt
gw_astrology-0.0.1.dist-info/top_level.txt
gw_astrology-0.0.1.dist-info/RECORD
