Metadata-Version: 2.1
Name: gw-astrology
Version: 0.0.1
Summary: Gravitational Wave Astrology
Home-page: https://git.ligo.org/rebecca.ewing/gw-astrology.git
Author: Becca Ewing
Author-email: rebecca.ewing@ligo.org
License: MIT
Classifier: Development Status :: 3 - Alpha
Classifier: Programming Language :: Python
Classifier: Programming Language :: Python :: 3
Classifier: Intended Audience :: Science/Research
Classifier: Natural Language :: English
Requires-Python: >=3.6
License-File: LICENSE
Requires-Dist: igwn-alert
Requires-Dist: hop-client
Requires-Dist: lalsuite
